[{"id":1, "pricePerHour":100,"bike":"Activa", "location":"kormangla",       "img":"images/Activa.jpeg"},
 {"id":2, "pricePerHour":200,"bike":"Access","location":"hebbal",            "img":"images/Access.jpeg"},
 {"id":3, "pricePerHour":150,"bike":"fascino","location":"Malleshwaram",     "img":"images/fascino.jpeg"},
 {"id":4, "pricePerHour":180,"bike":"Dio","location":"central bangalore",    "img":"images/Dio.jpeg"},
 {"id":5, "pricePerHour":200,"bike":"pulsor","location":"jayanagar",         "img":"images/Pulsor.jpeg"},
 {"id":6, "pricePerHour":250,"bike":"RoyalEnfeild", "location":"Maratahalli","img":"images/RoyalEnfeild.jpeg"},
 {"id":7, "pricePerHour":100,"bike": "Activa", "location":"Silk Board",      "img":"images/Activa.jpeg"},
 {"id":8, "pricePerHour":200,"bike": "Access", "location":"Electronic City", "img":"images/Access.jpeg"},
 {"id":9, "pricePerHour":150,"bike": "fascino","location":"madhura nagar",   "img":"images/fascino.jpeg"},
 {"id":10,"pricePerHour":180,"bike":"Dio", "location":"Jaya nagar",         "img":"images/Dio.jpeg"},
 {"id":11,"pricePerHour":200,"bike":"pulsor","location":"Indira nagar",     "img":"images/Pulsor.jpeg"},
 {"id":12,"pricePerHour":250,"bike":"RoyalEnfeild", "location":"jaya nagar","img":"images/RoyalEnfeild.jpeg"},
 {"id":13,"pricePerHour":100,"bike":"Activa", "location":"Silk Board",      "img":"images/Activa.jpeg"},
 {"id":14,"pricePerHour":200,"bike":"Access", "location":"Electronic City", "img":"images/Access.jpeg"},
 {"id":15,"pricePerHour":150,"bike":"fascino","location":"madhura nagar",   "img":"images/fascino.jpeg"},
 {"id":16,"pricePerHour":180,"bike":"Dio ","location":"Indira nagar",       "img":"images/Dio.jpeg"},
 {"id":17,"pricePerHour":200,"bike":"pulsor","location":"Madhura nagar",    "img":"images/Pulsor.jpeg"},
 {"id":18,"pricePerHour":250,"bike":"RoyalEnfeild ","location":"Silk Board","img":"images/RoyalEnfeild.jpeg"},
 {"id":19,"pricePerHour":100,"bike":"Activa", "location":"kormangla",        "img":"images/Activa.jpeg"},
 {"id":20,"pricePerHour":200,"bike":"Access","location":"hebbal",            "img":"images/Access.jpeg"},
 {"id":21,"pricePerHour":150,"bike":"fascino","location":"Malleshwaram",     "img":"images/fascino.jpeg"},
 {"id":22,"pricePerHour":180,"bike":"Dio","location":"central bangalore",    "img":"images/Dio.jpeg"},
 {"id":23,"pricePerHour":200,"bike":"pulsor","location":"jayanagar",         "img":"images/Pulsor.jpeg"},
 {"id":24,"pricePerHour":250,"bike":"RoyalEnfeild", "location":"Maratahalli","img":"images/RoyalEnfeild.jpeg"},
 {"id":25,"pricePerHour":100,"bike":"Activa", "location":"kormangla",        "img":"images/Activa.jpeg"},
 {"id":26,"pricePerHour":200,"bike":"Access","location":"hebbal",            "img":"images/Access.jpeg"},
 {"id":27,"pricePerHour":150,"bike":"fascino","location":"Malleshwaram",     "img":"images/fascino.jpeg"},
 {"id":28,"pricePerHour":180,"bike":"Dio","location":"central bangalore",    "img":"images/Dio.jpeg"},
 {"id":29,"pricePerHour":200,"bike":"pulsor","location":"jayanagar",         "img":"images/Pulsor.jpeg"},
 {"id":30,"pricePerHour":250,"bike":"RoyalEnfeild", "location":"Maratahalli","img":"images/RoyalEnfeild.jpeg"},
 {"id":31,"pricePerHour":100,"bike":"Activa", "location":"kormangla",       "img":"images/Activa.jpeg"},
 {"id":32,"pricePerHour":200,"bike":"Access","location":"hebbal",            "img":"images/Access.jpeg"},
 {"id":33,"pricePerHour":150,"bike":"fascino","location":"Malleshwaram",     "img":"images/fascino.jpeg"},
 {"id":34,"pricePerHour":180,"bike":"Dio","location":"central bangalore",    "img":"images/Dio.jpeg"},
 {"id":35,"pricePerHour":200,"bike":"pulsor","location":"jayanagar",         "img":"images/Pulsor.jpeg"},
 {"id":36,"pricePerHour":250,"bike":"RoyalEnfeild", "location":"Maratahalli","img":"images/RoyalEnfeild.jpeg"},
 {"id":37,"pricePerHour":100,"bike": "Activa", "location":"Silk Board",      "img":"images/Activa.jpeg"},
 {"id":38,"pricePerHour":200,"bike": "Access", "location":"Electronic City", "img":"images/Access.jpeg"},
 {"id":39,"pricePerHour":150,"bike": "fascino","location":"madhura nagar",   "img":"images/fascino.jpeg"},
 {"id":40,"pricePerHour":180,"bike":"Dio", "location":"Jaya nagar",         "img":"images/Dio.jpeg"},
 {"id":41,"pricePerHour":200,"bike":"pulsor","location":"Indira nagar",     "img":"images/Pulsor.jpeg"},
 {"id":42,"pricePerHour":250,"bike":"RoyalEnfeild", "location":"jaya nagar","img":"images/RoyalEnfeild.jpeg"},
 {"id":43,"pricePerHour":100,"bike":"Activa", "location":"Silk Board",      "img":"images/Activa.jpeg"},
 {"id":44,"pricePerHour":200,"bike":"Access", "location":"Electronic City", "img":"images/Access.jpeg"},
 {"id":45,"pricePerHour":150,"bike":"fascino","location":"madhura nagar",   "img":"images/fascino.jpeg"},
 {"id":46,"pricePerHour":180,"bike":"Dio ","location":"Indira nagar",       "img":"images/Dio.jpeg"},
 {"id":47,"pricePerHour":200,"bike":"pulsor","location":"Madhura nagar",    "img":"images/Pulsor.jpeg"},
 {"id":48,"pricePerHour":250,"bike":"RoyalEnfeild ","location":"Silk Board","img":"images/RoyalEnfeild.jpeg"},
 {"id":49,"pricePerHour":100,"bike":"Activa", "location":"kormangla",        "img":"images/Activa.jpeg"},
 {"id":50,"pricePerHour":200,"bike":"Access","location":"hebbal",            "img":"images/Access.jpeg"},
 {"id":51,"pricePerHour":150,"bike":"fascino","location":"Malleshwaram",     "img":"images/fascino.jpeg"},
 {"id":52,"pricePerHour":180,"bike":"Dio","location":"central bangalore",    "img":"images/Dio.jpeg"},
 {"id":53,"pricePerHour":200,"bike":"pulsor","location":"jayanagar",         "img":"images/Pulsor.jpeg"},
 {"id":54,"pricePerHour":250,"bike":"RoyalEnfeild", "location":"Maratahalli","img":"images/RoyalEnfeild.jpeg"},
 {"id":55,"pricePerHour":100,"bike":"Activa", "location":"kormangla",        "img":"images/Activa.jpeg"},
 {"id":56,"pricePerHour":200,"bike":"Access","location":"hebbal",            "img":"images/Access.jpeg"},
 {"id":57,"pricePerHour":150,"bike":"fascino","location":"Malleshwaram",     "img":"images/fascino.jpeg"},
 {"id":58,"pricePerHour":180,"bike":"Dio","location":"central bangalore",    "img":"images/Dio.jpeg"},
 {"id":59,"pricePerHour":200,"bike":"pulsor","location":"jayanagar",         "img":"images/Pulsor.jpeg"},
 {"id":60,"pricePerHour":250,"bike":"RoyalEnfeild", "location":"Maratahalli","img":"images/RoyalEnfeild.jpeg"},
 {"id":61,"pricePerHour":100,"bike":"Activa", "location":"kormangla",       "img":"images/Activa.jpeg"},
 {"id":62,"pricePerHour":200,"bike":"Access","location":"hebbal",            "img":"images/Access.jpeg"},
 {"id":63,"pricePerHour":150,"bike":"fascino","location":"Malleshwaram",     "img":"images/fascino.jpeg"},
 {"id":64,"pricePerHour":180,"bike":"Dio","location":"central bangalore",    "img":"images/Dio.jpeg"},
 {"id":65,"pricePerHour":200,"bike":"pulsor","location":"jayanagar",         "img":"images/Pulsor.jpeg"},
 {"id":66,"pricePerHour":250,"bike":"RoyalEnfeild", "location":"Maratahalli","img":"images/RoyalEnfeild.jpeg"},
 {"id":67,"pricePerHour":100,"bike": "Activa", "location":"Silk Board",      "img":"images/Activa.jpeg"},
 {"id":68,"pricePerHour":200,"bike": "Access", "location":"Electronic City", "img":"images/Access.jpeg"},
 {"id":69,"pricePerHour":150,"bike": "fascino","location":"madhura nagar",   "img":"images/fascino.jpeg"},
 {"id":70,"pricePerHour":180,"bike":"Dio", "location":"Jaya nagar",         "img":"images/Dio.jpeg"},
 {"id":71,"pricePerHour":200,"bike":"pulsor","location":"Indira nagar",     "img":"images/Pulsor.jpeg"},
 {"id":72,"pricePerHour":250,"bike":"RoyalEnfeild", "location":"jaya nagar","img":"images/RoyalEnfeild.jpeg"},
 {"id":73,"pricePerHour":100,"bike":"Activa", "location":"Silk Board",      "img":"images/Activa.jpeg"},
 {"id":74,"pricePerHour":200,"bike":"Access", "location":"Electronic City", "img":"images/Access.jpeg"},
 {"id":75,"pricePerHour":150,"bike":"fascino","location":"madhura nagar",   "img":"images/fascino.jpeg"},
 {"id":76,"pricePerHour":180,"bike":"Dio ","location":"Indira nagar",       "img":"images/Dio.jpeg"},
 {"id":77,"pricePerHour":200,"bike":"pulsor","location":"Madhura nagar",    "img":"images/Pulsor.jpeg"},
 {"id":78,"pricePerHour":250,"bike":"RoyalEnfeild ","location":"Silk Board","img":"images/RoyalEnfeild.jpeg"},
 {"id":79,"pricePerHour":100,"bike":"Activa", "location":"kormangla",        "img":"images/Activa.jpeg"},
 {"id":80,"pricePerHour":200,"bike":"Access","location":"hebbal",            "img":"images/Access.jpeg"},
 {"id":81,"pricePerHour":150,"bike":"fascino","location":"Malleshwaram",     "img":"images/fascino.jpeg"},
 {"id":82,"pricePerHour":180,"bike":"Dio","location":"central bangalore",    "img":"images/Dio.jpeg"},
 {"id":83,"pricePerHour":200,"bike":"pulsor","location":"jayanagar",         "img":"images/Pulsor.jpeg"},
 {"id":84,"pricePerHour":250,"bike":"RoyalEnfeild", "location":"Maratahalli","img":"images/RoyalEnfeild.jpeg"},
 {"id":85,"pricePerHour":100,"bike":"Activa", "location":"kormangla",        "img":"images/Activa.jpeg"},
 {"id":86,"pricePerHour":200,"bike":"Access","location":"hebbal",            "img":"images/Access.jpeg"},
 {"id":87,"pricePerHour":150,"bike":"fascino","location":"Malleshwaram",     "img":"images/fascino.jpeg"},
 {"id":88,"pricePerHour":180,"bike":"Dio","location":"central bangalore",    "img":"images/Dio.jpeg"},
 {"id":89,"pricePerHour":200,"bike":"pulsor","location":"jayanagar",         "img":"images/Pulsor.jpeg"},
 {"id":90,"pricePerHour":250,"bike":"RoyalEnfeild", "location":"Maratahalli","img":"images/RoyalEnfeild.jpeg"}]
